javascriptwebscraper/__init__.py
javascriptwebscraper/__main__.py
javascriptwebscraper-0.1.0.dist-info/DESCRIPTION.rst
javascriptwebscraper-0.1.0.dist-info/METADATA
javascriptwebscraper-0.1.0.dist-info/RECORD
javascriptwebscraper-0.1.0.dist-info/WHEEL
javascriptwebscraper-0.1.0.dist-info/entry_points.txt
javascriptwebscraper-0.1.0.dist-info/metadata.json
javascriptwebscraper-0.1.0.dist-info/top_level.txt
